{
	"name": "Ingest_bronze_Air_PollutionData",
	"properties": {
		"activities": [
			{
				"name": "GetAPIKey",
				"type": "WebActivity",
				"dependsOn": [],
				"policy": {
					"timeout": "0.12:00:00",
					"retry": 0,
					"retryIntervalInSeconds": 30,
					"secureOutput": false,
					"secureInput": false
				},
				"userProperties": [],
				"typeProperties": {
					"method": "GET",
					"url": "https://openweatherkv-ds598.vault.azure.net/secrets/OpenWeatherAPIKey?api-version=7.0",
					"authentication": {
						"type": "MSI",
						"resource": "https://vault.azure.net"
					}
				}
			},
			{
				"name": "ForEach1",
				"type": "ForEach",
				"dependsOn": [
					{
						"activity": "GetAPIKey",
						"dependencyConditions": [
							"Completed"
						]
					}
				],
				"userProperties": [],
				"typeProperties": {
					"items": {
						"value": "@range(1,53)",
						"type": "Expression"
					},
					"isSequential": true,
					"activities": [
						{
							"name": "Copy data1",
							"type": "Copy",
							"dependsOn": [],
							"policy": {
								"timeout": "0.12:00:00",
								"retry": 0,
								"retryIntervalInSeconds": 30,
								"secureOutput": false,
								"secureInput": false
							},
							"userProperties": [],
							"typeProperties": {
								"source": {
									"type": "JsonSource",
									"storeSettings": {
										"type": "HttpReadSettings",
										"requestMethod": "GET"
									},
									"formatSettings": {
										"type": "JsonReadSettings"
									}
								},
								"sink": {
									"type": "JsonSink",
									"storeSettings": {
										"type": "AzureBlobFSWriteSettings"
									},
									"formatSettings": {
										"type": "JsonWriteSettings"
									}
								},
								"enableStaging": false
							},
							"inputs": [
								{
									"referenceName": "Json3AirPollutionData",
									"type": "DatasetReference",
									"parameters": {
										"lat": "42.3601",
										"lon": "-71.0589",
										"start": "@div(sub(ticks(addDays(utcNow(), mul(-7, item()))), ticks('1970-01-01T00:00:00Z')), 10000000)",
										"end": "@div(sub(ticks(addDays(utcNow(), mul(-7, sub(item(), 1)))), ticks('1970-01-01T00:00:00Z')), 10000000)",
										"appid": "@activity('GetAPIKey').output.value"
									}
								}
							],
							"outputs": [
								{
									"referenceName": "Json4ADLSforAirPollutionData",
									"type": "DatasetReference",
									"parameters": {
										"filename": {
											"value": "airpollutiondata_@{div(sub(ticks(addDays(utcNow(), mul(-7, item()))), ticks('1970-01-01T00:00:00Z')), 10000000)}.json",
											"type": "Expression"
										}
									}
								}
							]
						}
					]
				}
			}
		],
		"annotations": []
	}
}